lf2i/__init__.py
lf2i/cli.py
lf2i/confidence_regions/__init__.py
lf2i/confidence_regions/neyman_inversion.py
lf2i/critical_values/__init__.py
lf2i/critical_values/nn_qr_algorithm.py
lf2i/critical_values/quantile_regression.py
lf2i/diagnostics/__init__.py
lf2i/diagnostics/diagnostics.py
lf2i/diagnostics/estimators.r
lf2i/inference/__init__.py
lf2i/inference/lf2i.py
lf2i/plot/__init__.py
lf2i/plot/coverage_diagnostics.py
lf2i/plot/miscellanea.py
lf2i/plot/parameter_regions.py
lf2i/simulator/__init__.py
lf2i/simulator/_base.py
lf2i/simulator/gaussian.py
lf2i/simulator/hep.py
lf2i/simulator/misc.py
lf2i/test_statistics/__init__.py
lf2i/test_statistics/_base.py
lf2i/test_statistics/_estimators.py
lf2i/test_statistics/acore.py
lf2i/test_statistics/bff.py
lf2i/test_statistics/waldo.py
lf2i/utils/__init__.py
lf2i/utils/calibration_diagnostics_inputs.py
lf2i/utils/miscellanea.py
lf2i/utils/odds_inputs.py
lf2i/utils/other_methods.py
lf2i/utils/waldo_inputs.py
lf2i-0.3.1.dist-info/LICENSE.txt
lf2i-0.3.1.dist-info/METADATA
lf2i-0.3.1.dist-info/WHEEL
lf2i-0.3.1.dist-info/entry_points.txt
lf2i-0.3.1.dist-info/top_level.txt
lf2i-0.3.1.dist-info/RECORD
