Metadata-Version: 2.1
Name: lf2i
Version: 0.3.1
Summary: Likelihood-Free Frequentist Inference
Home-page: https://github.com/lee-group-cmu/lf2i
Author: Luca Masserano, Niccolò Dalmasso, David Zhao, Rafael Izbicki, Ann B. Lee
Author-email: lee.group.cmu@gmail.com
License: MIT
Keywords: likelihood-free inference simulator likelihood posterior parameter
Requires-Python: >=3.9.0, <3.12
License-File: LICENSE.txt
Requires-Dist: alphashape
Requires-Dist: click
Requires-Dist: descartes
Requires-Dist: matplotlib >=3.6.0
Requires-Dist: numpy
Requires-Dist: rpy2 >=3.5.4
Requires-Dist: sbi >=0.19.2
Requires-Dist: scikit-learn
Requires-Dist: scipy
Requires-Dist: seaborn >=0.12.1
Requires-Dist: torch >=1.12.1
Requires-Dist: tqdm
Requires-Dist: xgboost >=1.6.2
Requires-Dist: joblib
Provides-Extra: dev
Requires-Dist: aquirdturtle-collapsible-headings ; extra == 'dev'
Requires-Dist: ipykernel ; extra == 'dev'
Requires-Dist: jupyterlab ; extra == 'dev'
Requires-Dist: furo ; extra == 'dev'
Requires-Dist: myst-parser ; extra == 'dev'
Requires-Dist: nbsphinx ; extra == 'dev'
Requires-Dist: pytest ; extra == 'dev'
Requires-Dist: sphinx ; extra == 'dev'
Requires-Dist: sphinx-mdinclude ; extra == 'dev'
